start_github/__init__.py
start_github/main.py
start_github/repository.py
start_github-0.0.2.dist-info/METADATA
start_github-0.0.2.dist-info/WHEEL
start_github-0.0.2.dist-info/RECORD
